article_extract/__init__.py
article_extract/__main__.py
article_extract/article_extract.py
article_extract/article_rules.yaml
article_extract-0.1.3.dist-info/LICENSE
article_extract-0.1.3.dist-info/METADATA
article_extract-0.1.3.dist-info/WHEEL
article_extract-0.1.3.dist-info/entry_points.txt
article_extract-0.1.3.dist-info/top_level.txt
article_extract-0.1.3.dist-info/RECORD
